{
  "providers": [
    {
      "type": "bitmap",
      "file": "minecraft:misc/hunger_half.png",
      "ascent": 8,
      "height": 16,
      "chars": [
        ""
      ]
    },
    {
      "type": "bitmap",
      "file": "minecraft:gui/sprites/hud/food_full.png",
      "ascent": 9,
      "height": 9,
      "chars": [
        ""
      ]
    },
    {
      "type": "bitmap",
      "file": "minecraft:misc/redstone.png",
      "ascent": 8,
      "height": 16,
      "chars": [
        ""
      ]
    },
    {
      "type": "bitmap",
      "file": "minecraft:misc/calcite_small.png",
      "ascent": 8,
      "height": 16,
      "chars": [
        ""
      ]
    }
  ]
}